Workbook

Sheet Questions
A1: ID | B1: Difficulty | C1: Question | D1: Est. input tokens | E1: Predicted output tokens | F1: Class | G1: Actual output tokens (fill after test) | H1: Error %
A2: Q001 | B2: Easy | C2: What is the capital of France? | D2: =ROUNDUP(LEN(C2)/Predictor!$B$4,0) -> 8 | E2: =ROUND(MAX(Predictor!$B$5,MIN(Predictor!$B$6,INDEX(Predictor!$B$12:$B$14,MATCH(B2,Predictor!$A$12:$A$14,0))*(1+Predictor!$B$7*SUMPRODUCT(--ISNUMBER(SEARCH(Predictor!$A$17:$A$35,C2))))/(1+Predictor!$B$8*SUMPRODUCT(--ISNUMBER(SEARCH(Predictor!$C$17:$C$21,C2)))))),0) -> 30 | F2: =IF(E2<=Predictor!$B$9,"interactive","batch") -> interactive | H2: =IF(G2="","",ABS(E2-G2)/G2)
A3: Q002 | B3: Easy | C3: What is 12 multiplied by 8? | D3: =ROUNDUP(LEN(C3)/Predictor!$B$4,0) -> 7 | E3: =ROUND(MAX(Predictor!$B$5,MIN(Predictor!$B$6,INDEX(Predictor!$B$12:$B$14,MATCH(B3,Predictor!$A$12:$A$14,0))*(1+Predictor!$B$7*SUMPRODUCT(--ISNUMBER(SEARCH(Predictor!$A$17:$A$35,C3))))/(1+Predictor!$B$8*SUMPRODUCT(--ISNUMBER(SEARCH(Predictor!$C$17:$C$21,C3)))))),0) -> 30 | F3: =IF(E3<=Predictor!$B$9,"interactive","batch") -> interactive | H3: =IF(G3="","",ABS(E3-G3)/G3)
A4: Q003 | B4: Easy | C4: Name the largest planet in our solar system. | D4: =ROUNDUP(LEN(C4)/Predictor!$B$4,0) -> 11 | E4: =ROUND(MAX(Predictor!$B$5,MIN(Predictor!$B$6,INDEX(Predictor!$B$12:$B$14,MATCH(B4,Predictor!$A$12:$A$14,0))*(1+Predictor!$B$7*SUMPRODUCT(--ISNUMBER(SEARCH(Predictor!$A$17:$A$35,C4))))/(1+Predictor!$B$8*SUMPRODUCT(--ISNUMBER(SEARCH(Predictor!$C$17:$C$21,C4)))))),0) -> 30 | F4: =IF(E4<=Predictor!$B$9,"interactive","batch") -> interactive | H4: =IF(G4="","",ABS(E4-G4)/G4)
A5: Q004 | B5: Easy | C5: Who wrote the play Romeo and Juliet? | D5: =ROUNDUP(LEN(C5)/Predictor!$B$4,0) -> 9 | E5: =ROUND(MAX(Predictor!$B$5,MIN(Predictor!$B$6,INDEX(Predictor!$B$12:$B$14,MATCH(B5,Predictor!$A$12:$A$14,0))*(1+Predictor!$B$7*SUMPRODUCT(--ISNUMBER(SEARCH(Predictor!$A$17:$A$35,C5))))/(1+Predictor!$B$8*SUMPRODUCT(--ISNUMBER(SEARCH(Predictor!$C$17:$C$21,C5)))))),0) -> 30 | F5: =IF(E5<=Predictor!$B$9,"interactive","batch") -> interactive | H5: =IF(G5="","",ABS(E5-G5)/G5)
A6: Q005 | B6: Easy | C6: What is the chemical symbol for gold? | D6: =ROUNDUP(LEN(C6)/Predictor!$B$4,0) -> 10 | E6: =ROUND(MAX(Predictor!$B$5,MIN(Predictor!$B$6,INDEX(Predictor!$B$12:$B$14,MATCH(B6,Predictor!$A$12:$A$14,0))*(1+Predictor!$B$7*SUMPRODUCT(--ISNUMBER(SEARCH(Predictor!$A$17:$A$35,C6))))/(1+Predictor!$B$8*SUMPRODUCT(--ISNUMBER(SEARCH(Predictor!$C$17:$C$21,C6)))))),0) -> 30 | F6: =IF(E6<=Predictor!$B$9,"interactive","batch") -> interactive | H6: =IF(G6="","",ABS(E6-G6)/G6)
A7: Q006 | B7: Easy | C7: How many days are there in a leap year? | D7: =ROUNDUP(LEN(C7)/Predictor!$B$4,0) -> 10 | E7: =ROUND(MAX(Predictor!$B$5,MIN(Predictor!$B$6,INDEX(Predictor!$B$12:$B$14,MATCH(B7,Predictor!$A$12:$A$14,0))*(1+Predictor!$B$7*SUMPRODUCT(--ISNUMBER(SEARCH(Predictor!$A$17:$A$35,C7))))/(1+Predictor!$B$8*SUMPRODUCT(--ISNUMBER(SEARCH(Predictor!$C$17:$C$21,C7)))))),0) -> 30 | F7: =IF(E7<=Predictor!$B$9,"interactive","batch") -> interactive | H7: =IF(G7="","",ABS(E7-G7)/G7)
A8: Q007 | B8: Easy | C8: What color do you get by mixing blue and yellow? | D8: =ROUNDUP(LEN(C8)/Predictor!$B$4,0) -> 12 | E8: =ROUND(MAX(Predictor!$B$5,MIN(Predictor!$B$6,INDEX(Predictor!$B$12:$B$14,MATCH(B8,Predictor!$A$12:$A$14,0))*(1+Predictor!$B$7*SUMPRODUCT(--ISNUMBER(SEARCH(Predictor!$A$17:$A$35,C8))))/(1+Predictor!$B$8*SUMPRODUCT(--ISNUMBER(SEARCH(Predictor!$C$17:$C$21,C8)))))),0) -> 30 | F8: =IF(E8<=Predictor!$B$9,"interactive","batch") -> interactive | H8: =IF(G8="","",ABS(E8-G8)/G8)
A9: Q008 | B9: Easy | C9: What is the opposite of "ancient"? | D9: =ROUNDUP(LEN(C9)/Predictor!$B$4,0) -> 9 | E9: =ROUND(MAX(Predictor!$B$5,MIN(Predictor!$B$6,INDEX(Predictor!$B$12:$B$14,MATCH(B9,Predictor!$A$12:$A$14,0))*(1+Predictor!$B$7*SUMPRODUCT(--ISNUMBER(SEARCH(Predictor!$A$17:$A$35,C9))))/(1+Predictor!$B$8*SUMPRODUCT(--ISNUMBER(SEARCH(Predictor!$C$17:$C$21,C9)))))),0) -> 30 | F9: =IF(E9<=Predictor!$B$9,"interactive","batch") -> interactive | H9: =IF(G9="","",ABS(E9-G9)/G9)
A10: Q009 | B10: Easy | C10: Translate "good morning" into Spanish. | D10: =ROUNDUP(LEN(C10)/Predictor!$B$4,0) -> 10 | E10: =ROUND(MAX(Predictor!$B$5,MIN(Predictor!$B$6,INDEX(Predictor!$B$12:$B$14,MATCH(B10,Predictor!$A$12:$A$14,0))*(1+Predictor!$B$7*SUMPRODUCT(--ISNUMBER(SEARCH(Predictor!$A$17:$A$35,C10))))/(1+Predictor!$B$8*SUMPRODUCT(--ISNUMBER(SEARCH(Predictor!$C$17:$C$21,C10)))))),0) -> 30 | F10: =IF(E10<=Predictor!$B$9,"interactive","batch") -> interactive | H10: =IF(G10="","",ABS(E10-G10)/G10)
A11: Q010 | B11: Easy | C11: What is the boiling point of water in Celsius? | D11: =ROUNDUP(LEN(C11)/Predictor!$B$4,0) -> 12 | E11: =ROUND(MAX(Predictor!$B$5,MIN(Predictor!$B$6,INDEX(Predictor!$B$12:$B$14,MATCH(B11,Predictor!$A$12:$A$14,0))*(1+Predictor!$B$7*SUMPRODUCT(--ISNUMBER(SEARCH(Predictor!$A$17:$A$35,C11))))/(1+Predictor!$B$8*SUMPRODUCT(--ISNUMBER(SEARCH(Predictor!$C$17:$C$21,C11)))))),0) -> 30 | F11: =IF(E11<=Predictor!$B$9,"interactive","batch") -> interactive | H11: =IF(G11="","",ABS(E11-G11)/G11)
A12: Q011 | B12: Easy | C12: Which ocean is the largest? | D12: =ROUNDUP(LEN(C12)/Predictor!$B$4,0) -> 7 | E12: =ROUND(MAX(Predictor!$B$5,MIN(Predictor!$B$6,INDEX(Predictor!$B$12:$B$14,MATCH(B12,Predictor!$A$12:$A$14,0))*(1+Predictor!$B$7*SUMPRODUCT(--ISNUMBER(SEARCH(Predictor!$A$17:$A$35,C12))))/(1+Predictor!$B$8*SUMPRODUCT(--ISNUMBER(SEARCH(Predictor!$C$17:$C$21,C12)))))),0) -> 30 | F12: =IF(E12<=Predictor!$B$9,"interactive","batch") -> interactive | H12: =IF(G12="","",ABS(E12-G12)/G12)
A13: Q012 | B13: Easy | C13: What is the square root of 81? | D13: =ROUNDUP(LEN(C13)/Predictor!$B$4,0) -> 8 | E13: =ROUND(MAX(Predictor!$B$5,MIN(Predictor!$B$6,INDEX(Predictor!$B$12:$B$14,MATCH(B13,Predictor!$A$12:$A$14,0))*(1+Predictor!$B$7*SUMPRODUCT(--ISNUMBER(SEARCH(Predictor!$A$17:$A$35,C13))))/(1+Predictor!$B$8*SUMPRODUCT(--ISNUMBER(SEARCH(Predictor!$C$17:$C$21,C13)))))),0) -> 30 | F13: =IF(E13<=Predictor!$B$9,"interactive","batch") -> interactive | H13: =IF(G13="","",ABS(E13-G13)/G13)
... A151: Q150 | B151: Hard | C151: Create a detailed disaster recovery document for a small company's IT infrastructure, including backup strategy, recovery objectives, roles and testing procedures. | D151: =ROUNDUP(LEN(C151)/Predictor!$B$4,0) -> 41 | E151: =ROUND(MAX(Predictor!$B$5,MIN(Predictor!$B$6,INDEX(Predictor!$B$12:$B$14,MATCH(B151,Predictor!$A$12:$A$14,0))*(1+Predictor!$B$7*SUMPRODUCT(--ISNUMBER(SEARCH(Predictor!$A$17:$A$35,C151))))/(1+Predictor!$B$8*SUMPRODUCT(--ISNUMBER(SEARCH(Predictor!$C$17:$C$21,C151)))))),0) -> 840 | F151: =IF(E151<=Predictor!$B$9,"interactive","batch") -> batch | H151: =IF(G151="","",ABS(E151-G151)/G151)

Sheet Predictor
A1: Output-token predictor: assumptions (blue = editable input)
A3: Assumption | B3: Value | C3: Note
A4: Characters per token | B4: 4 | C4: Rule of thumb for English text (about 4 chars or 0.75 words per token). Replace with your model's real tokenizer ratio.
A5: Minimum output tokens | B5: 5 | C5: Floor so a prediction is never 0.
A6: Maximum output tokens (cap) | B6: 1500 | C6: Should match your max_tokens limit in the gateway.
A7: Boost per long-answer keyword | B7: 0.2 | C7: Each keyword found multiplies the base by (1 + boost). Starting guess, tune it.
A8: Reduction per short-answer keyword | B8: 0.5 | C8: Each keyword found divides the result by (1 + reduction). Starting guess, tune it.
A9: Interactive threshold (tokens) | B9: 100 | C9: Predicted output at or below this = 'interactive', above = 'batch'.
A11: Difficulty | B11: Base output tokens | C11: Note
A12: Easy | B12: 30 | C12: Starting guess for typical answer length. Replace with the average of your real measurements.
A13: Medium | B13: 200 | C13: Starting guess for typical answer length. Replace with the average of your real measurements.
A14: Hard | B14: 700 | C14: Starting guess for typical answer length. Replace with the average of your real measurements.
A16: Long-answer keywords (raise prediction) | C16: Short-answer keywords (lower prediction)
A17: explain | C17: briefly
A18: step | C18: one word
A19: compare | C19: one sentence
A20: detail | C20: yes or no
A21: example | C21: in short
A22: list
A23: write
A24: design
A25: implement
A26: essay
A27: analyze
A28: describe
A29: why
A30: in depth
A31: comprehensive
A32: tutorial
A33: guide
... A38: Note: formulas use the exact ranges A17:A35 and C17:C21. If you add keywords, extend those ranges (blank cells would count as a match).

Sheet Summary
A1: Summary (all values are formulas)
A3: Difficulty | B3: Questions | C3: Avg input tokens | D3: Avg predicted output tokens | E3: Total predicted output tokens | F3: Interactive count
A4: Easy | B4: =COUNTIF(Questions!$B$2:$B$151,A4) -> 50 | C4: =AVERAGEIF(Questions!$B$2:$B$151,A4,Questions!$D$2:$D$151) -> 9 | D4: =AVERAGEIF(Questions!$B$2:$B$151,A4,Questions!$E$2:$E$151) -> 30 | E4: =SUMIF(Questions!$B$2:$B$151,A4,Questions!$E$2:$E$151) -> 1500 | F4: =COUNTIFS(Questions!$B$2:$B$151,A4,Questions!$F$2:$F$151,"interactive") -> 50
A5: Medium | B5: =COUNTIF(Questions!$B$2:$B$151,A5) -> 50 | C5: =AVERAGEIF(Questions!$B$2:$B$151,A5,Questions!$D$2:$D$151) -> 15.74 | D5: =AVERAGEIF(Questions!$B$2:$B$151,A5,Questions!$E$2:$E$151) -> 246.14 | E5: =SUMIF(Questions!$B$2:$B$151,A5,Questions!$E$2:$E$151) -> 12307 | F5: =COUNTIFS(Questions!$B$2:$B$151,A5,Questions!$F$2:$F$151,"interactive") -> 0
A6: Hard | B6: =COUNTIF(Questions!$B$2:$B$151,A6) -> 50 | C6: =AVERAGEIF(Questions!$B$2:$B$151,A6,Questions!$D$2:$D$151) -> 34.3 | D6: =AVERAGEIF(Questions!$B$2:$B$151,A6,Questions!$E$2:$E$151) -> 988.4 | E6: =SUMIF(Questions!$B$2:$B$151,A6,Questions!$E$2:$E$151) -> 49420 | F6: =COUNTIFS(Questions!$B$2:$B$151,A6,Questions!$F$2:$F$151,"interactive") -> 0
A7: Total | B7: =SUM(B4:B6) -> 150 | C7: =AVERAGE(Questions!$D$2:$D$151) -> 19.68 | D7: =AVERAGE(Questions!$E$2:$E$151) -> 421.51333 | E7: =SUM(E4:E6) -> 63227 | F7: =SUM(F4:F6) -> 50
A10: Calibration (after you run the questions on your model and fill column G on the Questions sheet)
A11: Questions with actual tokens | B11: =COUNT(Questions!$G$2:$G$151) -> 0
A12: Average error (MAPE) | B12: =IFERROR(AVERAGE(Questions!$H$2:$H$151),"fill column G first") -> fill column G first
A13: Calibration multiplier (actual / predicted) | B13: =IFERROR(SUM(Questions!$G$2:$G$151)/SUMIF(Questions!$G$2:$G$151,">0",Questions!$E$2:$E$151),"fill column G first") -> fill column G first
A14: Multiply every base token value on Predictor by this number, then compare the error again.

Sheet Formula Guide
A1: How to predict output tokens with a formula
A3: Step 1: Input tokens (known before the request runs)
A4: Input tokens = ROUNDUP(number of characters / chars per token, 0). With about 4 characters per token for English. Used in column D.
A6: Step 2: Predicted output tokens (needed by the scheduler before the request runs)
A7: Predicted = MIN(cap, MAX(floor, Base[difficulty] x (1 + boost x LongKeywordCount) / (1 + reduction x ShortKeywordCount)))
A8: Base[difficulty]: typical answer length for Easy / Medium / Hard (Predictor sheet).
A9: LongKeywordCount: how many words like explain, detail, write, design, implement appear in the prompt (each one raises the answer length).
A10: ShortKeywordCount: how many words like briefly, one word, yes or no appear (each one shortens the answer).
A11: Used in column E.
A13: Step 3: Scheduler class
A14: Class = interactive if Predicted <= threshold, otherwise batch. Use this to set priority and weight in the scheduler (column F).
A16: Step 4: Calibrate with real data (this is what makes the prediction credible)
... A25: Be honest on the slides: this is a heuristic estimate, not an exact value. Report the measured error (MAPE) from the Summary sheet.
